tradingbutler/__init__.py
tradingbutler/summary.py
tradingbutler/templates/template.html
tradingbutler/tests/__init__.py
tradingbutler/tests/tests.py
tradingbutler-0.1.14.dist-info/LICENSE
tradingbutler-0.1.14.dist-info/METADATA
tradingbutler-0.1.14.dist-info/WHEEL
tradingbutler-0.1.14.dist-info/RECORD
