Metadata-Version: 2.1
Name: tradingbutler
Version: 0.1.14
Summary: 
Home-page: https://github.com/Robinhuo1/tradingbutler
License: MIT
Author: Robin Huo
Requires-Python: >=3.8,<4.0
Classifier: License :: OSI Approved :: MIT License
Classifier: Programming Language :: Python :: 3
Classifier: Programming Language :: Python :: 3.8
Classifier: Programming Language :: Python :: 3.9
Classifier: Programming Language :: Python :: 3.10
Classifier: Programming Language :: Python :: 3.11
Requires-Dist: Jinja2 (>=3.1.2,<4.0.0)
Requires-Dist: python-dateutil (>=2.8.2,<3.0.0)
